Metadata-Version: 2.4
Name: syned-gui-2
Version: 1.0.2
Summary: SYNED (SYNchrotron Elements Dictionary) gui library
Home-page: https://github.com/oasys-kit/syned-gui-2
Download-URL: https://github.com/oasys-kit/syned-gui-2
Author: Manuel Sanchez del Rio, Luca Rebuffi
Author-email: lrebuffi@anl.gov
Maintainer: L Rebuffi and M Sanchez del Rio
Maintainer-email: lrebuffi@anl.gov
License: BSD
Keywords: dictionary,glossary,synchrotronsimulation
Classifier: Development Status :: 5 - Production/Stable
Classifier: Environment :: Console
Classifier: Environment :: Plugins
Classifier: Programming Language :: Python :: 3
Classifier: License :: OSI Approved :: GNU General Public License v3 or later (GPLv3+)
Classifier: Operating System :: POSIX
Classifier: Operating System :: Microsoft :: Windows
Classifier: Topic :: Scientific/Engineering :: Visualization
Classifier: Topic :: Software Development :: Libraries :: Python Modules
Classifier: Intended Audience :: Education
Classifier: Intended Audience :: Science/Research
Classifier: Intended Audience :: Developers
License-File: LICENSE
Requires-Dist: setuptools
Requires-Dist: oasys2>=0.0.1
Dynamic: author
Dynamic: author-email
Dynamic: classifier
Dynamic: description
Dynamic: download-url
Dynamic: home-page
Dynamic: keywords
Dynamic: license
Dynamic: license-file
Dynamic: maintainer
Dynamic: maintainer-email
Dynamic: requires-dist
Dynamic: summary
